Metadata-Version: 2.1
Name: wsco
Version: 0.0.1
Summary: Useful api client on terminal
Home-page: https://github.com/wxnacy/wsco
Author: wxnacy
Author-email: wxnacy@gmail.com
License: MIT
Platform: UNKNOWN
Classifier: License :: OSI Approved :: MIT License
Classifier: Programming Language :: Python
Classifier: Programming Language :: Python :: 3
Classifier: Programming Language :: Python :: 3.6
Classifier: Programming Language :: Python :: 3.7
Classifier: Programming Language :: Python :: Implementation :: CPython
Classifier: Programming Language :: Python :: Implementation :: PyPy
Requires-Python: >=3.6.0
